pypiwrap/__init__.py
pypiwrap/client.py
pypiwrap/consts.py
pypiwrap/exceptions.py
pypiwrap/utils.py
pypiwrap/objects/__init__.py
pypiwrap/objects/base.py
pypiwrap/objects/pypi.py
pypiwrap/objects/rss.py
pypiwrap/objects/simple_repo.py
pypiwrap-2.0.0.dist-info/LICENSE
pypiwrap-2.0.0.dist-info/METADATA
pypiwrap-2.0.0.dist-info/WHEEL
pypiwrap-2.0.0.dist-info/top_level.txt
pypiwrap-2.0.0.dist-info/RECORD
