Metadata-Version: 2.2
Name: pypiwrap
Version: 2.0.0
Summary: An API wrapper for the Python Package Index
Author-email: Angel Carias <lotta.dev@outlook.com>
License: MIT License
Project-URL: Homepage, https://github.com/aescarias/pypiwrap
Project-URL: Changelog, https://github.com/aescarias/pypiwrap/blob/main/CHANGELOG.md
Project-URL: Documentation, https://pypiwrap.rtfd.io/
Classifier: Intended Audience :: Developers
Classifier: Operating System :: OS Independent
Classifier: License :: OSI Approved :: MIT License
Classifier: Programming Language :: Python :: 3.9
Classifier: Programming Language :: Python :: 3.10
Classifier: Programming Language :: Python :: 3.11
Classifier: Programming Language :: Python :: 3.12
Classifier: Programming Language :: Python :: 3.13
Requires-Python: >=3.9
License-File: LICENSE
Requires-Dist: requests>=2.32.0
Provides-Extra: docs
Requires-Dist: Sphinx>=8.1.0; extra == "docs"
Requires-Dist: sphinx-design>=0.6.0; extra == "docs"
Requires-Dist: furo>=2024.8.6; extra == "docs"
Requires-Dist: sphinx-copybutton>=0.5.2; extra == "docs"
Provides-Extra: tests
Requires-Dist: pytest-cov>=6.0; extra == "tests"
Requires-Dist: pytest>=8.0; extra == "tests"
Requires-Dist: tox>=4.20; extra == "tests"
